LICENSE.md
README.md
setup.py
ceotr_notifications/__init__.py
ceotr_notifications/slack_message.py
ceotr_notifications.egg-info/PKG-INFO
ceotr_notifications.egg-info/SOURCES.txt
ceotr_notifications.egg-info/dependency_links.txt
ceotr_notifications.egg-info/requires.txt
ceotr_notifications.egg-info/top_level.txt
ceotr_notifications.egg-info/zip-safe